{
    "/backend/assets/css/reset.css": "/backend/assets/css/reset.css?id=3537f958f4cc0649ea1b",
    "/backend/assets/css/boot.css": "/backend/assets/css/boot.css?id=09d70ea1447350e734d2",
    "/backend/assets/css/login.css": "/backend/assets/css/login.css?id=06a16240f7cb4229bf9f",
    "/backend/assets/css/style.css": "/backend/assets/css/style.css?id=2582216052cda9547b13",
    "/backend/assets/css/toastr.css": "/backend/assets/css/toastr.css?id=9fd6bb4375425bd19660",
    "/backend/assets/css/libs.css": "/backend/assets/css/libs.css?id=e475e7021e891f029879",
    "/backend/assets/js/jquery.js": "/backend/assets/js/jquery.js?id=a09e13ee94d51c524b7e",
    "/backend/assets/js/login.js": "/backend/assets/js/login.js?id=c92ce32afa96f137d311",
    "/backend/assets/js/toastr.js": "/backend/assets/js/toastr.js?id=91cca45211e48faee922",
    "/backend/assets/js/libs.js": "/backend/assets/js/libs.js?id=6fb5522ffcc05e93e2c5",
    "/backend/assets/js/scripts.js": "/backend/assets/js/scripts.js?id=66aa7114f282c45b8fa4"
}
